{"errors":[],"warnings":[],"namedChunkGroups":{"app":{"chunks":[7,0,6,2],"assets":["webpack-runtime-1aeaad2f2b41ec6350ce.js","webpack-runtime-1aeaad2f2b41ec6350ce.js.map","styles.f3cfd644cdc7a9a5373b.css","styles-89fd2ae28bdf06750a71.js","styles-89fd2ae28bdf06750a71.js.map","framework-868c53fff4771b0bde98.js","framework-868c53fff4771b0bde98.js.map","app-5677d527dec45cd7226e.js","app-5677d527dec45cd7226e.js.map"],"children":{},"childAssets":{}},"component---src-pages-404-jsx":{"chunks":[0,1,3],"assets":["styles.f3cfd644cdc7a9a5373b.css","styles-89fd2ae28bdf06750a71.js","styles-89fd2ae28bdf06750a71.js.map","commons-099a154146b5ff72b1ad.js","commons-099a154146b5ff72b1ad.js.map","component---src-pages-404-jsx-c4f2acc888c505a4ae83.js","component---src-pages-404-jsx-c4f2acc888c505a4ae83.js.map"],"children":{},"childAssets":{}},"component---src-pages-index-jsx":{"chunks":[0,1,4],"assets":["styles.f3cfd644cdc7a9a5373b.css","styles-89fd2ae28bdf06750a71.js","styles-89fd2ae28bdf06750a71.js.map","commons-099a154146b5ff72b1ad.js","commons-099a154146b5ff72b1ad.js.map","component---src-pages-index-jsx-19f62d564e9abded34d6.js","component---src-pages-index-jsx-19f62d564e9abded34d6.js.map"],"children":{},"childAssets":{}},"component---src-templates-project-jsx":{"chunks":[0,1,5],"assets":["styles.f3cfd644cdc7a9a5373b.css","styles-89fd2ae28bdf06750a71.js","styles-89fd2ae28bdf06750a71.js.map","commons-099a154146b5ff72b1ad.js","commons-099a154146b5ff72b1ad.js.map","component---src-templates-project-jsx-349eaf2d30a3367dbf2b.js","component---src-templates-project-jsx-349eaf2d30a3367dbf2b.js.map"],"children":{},"childAssets":{}}},"assetsByChunkName":{"app":["webpack-runtime-1aeaad2f2b41ec6350ce.js","styles.f3cfd644cdc7a9a5373b.css","styles-89fd2ae28bdf06750a71.js","framework-868c53fff4771b0bde98.js","app-5677d527dec45cd7226e.js"],"component---src-pages-404-jsx":["styles.f3cfd644cdc7a9a5373b.css","styles-89fd2ae28bdf06750a71.js","commons-099a154146b5ff72b1ad.js","component---src-pages-404-jsx-c4f2acc888c505a4ae83.js"],"component---src-pages-index-jsx":["styles.f3cfd644cdc7a9a5373b.css","styles-89fd2ae28bdf06750a71.js","commons-099a154146b5ff72b1ad.js","component---src-pages-index-jsx-19f62d564e9abded34d6.js"],"component---src-templates-project-jsx":["styles.f3cfd644cdc7a9a5373b.css","styles-89fd2ae28bdf06750a71.js","commons-099a154146b5ff72b1ad.js","component---src-templates-project-jsx-349eaf2d30a3367dbf2b.js"]}}